gcloud_realtimestt/__init__.py
gcloud_realtimestt/src/__init__.py
gcloud_realtimestt/src/gcloud_realtimestt.py
gcloud_realtimestt-0.3.0.dist-info/LICENSE
gcloud_realtimestt-0.3.0.dist-info/METADATA
gcloud_realtimestt-0.3.0.dist-info/WHEEL
gcloud_realtimestt-0.3.0.dist-info/top_level.txt
gcloud_realtimestt-0.3.0.dist-info/RECORD
