Metadata-Version: 2.1
Name: gcloud-realtimestt
Version: 0.3.0
Summary: A python library for realtime transcription from and audio stream using google-cloud-speech API
Author: Zuhaib Khan
License: MIT
Classifier: License :: OSI Approved :: MIT License
Classifier: Programming Language :: Python :: 3.10
Classifier: Operating System :: OS Independent
Requires-Python: >=3.10
License-File: LICENSE
Requires-Dist: google-cloud-speech ==2.29.0
